tmp_clear/__init__.py
tmp_clear/haha.py
ex4-0.0.1.dist-info/METADATA
ex4-0.0.1.dist-info/WHEEL
ex4-0.0.1.dist-info/top_level.txt
ex4-0.0.1.dist-info/RECORD
